<Properties StartupConfiguration="{5B9FF267-005F-A3BF-219E-FEAE2D8C894F}|Unit Tests">
  <MonoDevelop.Ide.Workbench ActiveDocument="Assets/Scripts/Shooting.cs">
    <Files>
      <File FileName="Assets/Scripts/Player.cs" Line="34" Column="21" />
      <File FileName="Assets/Scripts/Projectile.cs" Line="21" Column="5" />
      <File FileName="Assets/Scripts/Shooting.cs" Line="67" Column="11" />
    </Files>
  </MonoDevelop.Ide.Workbench>
  <MonoDevelop.Ide.DebuggingService.PinnedWatches />
  <MonoDevelop.Ide.Workspace ActiveConfiguration="Debug" />
  <MonoDevelop.Ide.ItemProperties.Assembly-CSharp PreferredExecutionTarget="MonoDevelop.Default" />
  <MonoDevelop.Ide.DebuggingService.Breakpoints>
    <BreakpointStore />
  </MonoDevelop.Ide.DebuggingService.Breakpoints>
  <MultiItemStartupConfigurations />
</Properties>